quirk/__init__.py
quirk/base.py
quirk/classifier.py
quirk/notebook.py
quirk/regressor.py
quirk/terminal.py
quirk-0.1.3.dist-info/LICENSE.txt
quirk-0.1.3.dist-info/METADATA
quirk-0.1.3.dist-info/WHEEL
quirk-0.1.3.dist-info/top_level.txt
quirk-0.1.3.dist-info/RECORD
