Metadata-Version: 2.1
Name: quirk
Version: 0.1.3
Summary: Build powerful predictive models with a few lines of code
Home-page: https://github.com/ankane/quirk
Author: Andrew Kane
Author-email: andrew@chartkick.com
License: MIT
Platform: UNKNOWN
Requires-Dist: pandas
Requires-Dist: seaborn
Requires-Dist: scikit-learn
Requires-Dist: matplotlib
Requires-Dist: scipy
